dpcolors/__init__.py
dpcolors/grammars/__init__.py
dpcolors/grammars/dp.py
dpcolors/grammars/irc.py
python_dpcolors-0.1.1.dist-info/DESCRIPTION.rst
python_dpcolors-0.1.1.dist-info/METADATA
python_dpcolors-0.1.1.dist-info/RECORD
python_dpcolors-0.1.1.dist-info/WHEEL
python_dpcolors-0.1.1.dist-info/metadata.json
python_dpcolors-0.1.1.dist-info/top_level.txt
tests/__init__.py
tests/conftest.py
tests/test_conversion.py
tests/test_dp.py
tests/test_irc.py
