Metadata-Version: 2.0
Name: python-dpcolors
Version: 0.1.1
Summary: library to convert Xonotic color strings to various other formats
Home-page: https://github.com/nsavch/python-dpcolors
Author: Nick Savchenko
Author-email: nsavch@gmail.com
License: GPLv3
Keywords: xonotic
Platform: UNKNOWN
Classifier: Development Status :: 4 - Beta
Classifier: Environment :: Console
Classifier: Intended Audience :: System Administrators
Classifier: Intended Audience :: Developers
Classifier: Intended Audience :: Other Audience
Classifier: License :: OSI Approved :: GNU General Public License v3 (GPLv3)
Classifier: Operating System :: POSIX
Classifier: Programming Language :: Python :: 3.4
Classifier: Programming Language :: Python :: 3.5
Classifier: Programming Language :: Python :: 3.6
Classifier: Programming Language :: Python :: 3 :: Only
Classifier: Programming Language :: Python :: Implementation :: CPython
Classifier: Topic :: Software Development :: Libraries
Classifier: Topic :: Games/Entertainment
Requires-Dist: ansicolors
Requires-Dist: setuptools
